eg4_python/__init__.py
eg4_python/client.py
eg4_python/constants.py
eg4_python/exceptions.py
eg4_python/models.py
eg4_python-0.1.2.dist-info/licenses/LICENSE
eg4_python-0.1.2.dist-info/METADATA
eg4_python-0.1.2.dist-info/WHEEL
eg4_python-0.1.2.dist-info/top_level.txt
eg4_python-0.1.2.dist-info/RECORD
