Metadata-Version: 2.4
Name: eg4-python
Version: 0.1.2
Summary: Python client for EG4 solar inverter monitoring with async/sync support
Author-email: Matt Dreyer <matt_dreyer@hotmail.com>
License: Apache-2.0
Project-URL: Homepage, https://github.com/matt-dreyer/eg4_python
Project-URL: Documentation, https://github.com/matt-dreyer/eg4_python
Project-URL: Repository, https://github.com/matt-dreyer/eg4_python
Project-URL: Bug Tracker, https://github.com/matt-dreyer/eg4_python/issues
Keywords: eg4,solar,inverter,monitoring,api,async,home-assistant
Classifier: Development Status :: 4 - Beta
Classifier: Intended Audience :: Developers
Classifier: License :: OSI Approved :: Apache Software License
Classifier: Operating System :: OS Independent
Classifier: Programming Language :: Python :: 3
Classifier: Programming Language :: Python :: 3.8
Classifier: Programming Language :: Python :: 3.9
Classifier: Programming Language :: Python :: 3.10
Classifier: Programming Language :: Python :: 3.11
Classifier: Programming Language :: Python :: 3.12
Classifier: Topic :: Software Development :: Libraries :: Python Modules
Classifier: Topic :: System :: Monitoring
Classifier: Topic :: Home Automation
Classifier: Topic :: Scientific/Engineering
Classifier: Framework :: AsyncIO
Requires-Python: >=3.8
License-File: LICENSE
Requires-Dist: aiohttp>=3.8.0
Requires-Dist: python-dotenv>=0.19.0
Provides-Extra: dev
Requires-Dist: pytest>=7.0.0; extra == "dev"
Requires-Dist: pytest-asyncio>=0.21.0; extra == "dev"
Requires-Dist: pytest-cov>=4.0.0; extra == "dev"
Requires-Dist: ruff>=0.1.0; extra == "dev"
Requires-Dist: mypy>=1.0.0; extra == "dev"
Requires-Dist: black>=22.0.0; extra == "dev"
Requires-Dist: pre-commit>=2.20.0; extra == "dev"
Dynamic: license-file
